README.rst
setup.py
pyhub/__init__.py
pyhub/arithmetic.py
pyhub.egg-info/PKG-INFO
pyhub.egg-info/SOURCES.txt
pyhub.egg-info/dependency_links.txt
pyhub.egg-info/top_level.txt
pyhub.egg-info/zip-safe