Metadata-Version: 1.1
Name: pyhub
Version: 0.0.10
Summary: this is a simple tool for python.
Home-page: https://github.com/mengtianwxs/pyhub
Author: mengtianwxs
Author-email: 374835063@qq.com
License: MIT
Keywords: pyhub
Platform: UNKNOWN
Classifier: License :: OSI Approved :: MIT License
Classifier: Programming Language :: Python
Classifier: Intended Audience :: Developers
Classifier: Operating System :: OS Independent
